docker_links.py
docker_links_python-0.1.0.dist-info/RECORD
docker_links_python-0.1.0.dist-info/METADATA
docker_links_python-0.1.0.dist-info/top_level.txt
docker_links_python-0.1.0.dist-info/DESCRIPTION.rst
docker_links_python-0.1.0.dist-info/WHEEL
docker_links_python-0.1.0.dist-info/metadata.json
